fibonacci_ast_visualizer/__init__.py
fibonacci_ast_visualizer/fibonacci.py
fibonacci_ast_visualizer/visualize.py
fibonacci_ast_visualizer-0.3.4.dist-info/METADATA
fibonacci_ast_visualizer-0.3.4.dist-info/WHEEL
fibonacci_ast_visualizer-0.3.4.dist-info/top_level.txt
fibonacci_ast_visualizer-0.3.4.dist-info/RECORD
