Metadata-Version: 2.1
Name: fibonacci-ast-visualizer
Version: 0.3.4
Summary: UNKNOWN
Home-page: https://github.com/zhvkgj/advance-python-itmo-2022
Author: Sergey Sokolvyak
License: UNKNOWN
Keywords: fibonacci,ast,networkx
Platform: UNKNOWN
Requires-Dist: astunparse (==1.6.3)
Requires-Dist: cycler (==0.11.0)
Requires-Dist: fonttools (==4.29.1)
Requires-Dist: kiwisolver (==1.3.2)
Requires-Dist: matplotlib (==3.5.1)
Requires-Dist: networkx (==2.6.3)
Requires-Dist: numpy (==1.22.1)
Requires-Dist: packaging (==21.3)
Requires-Dist: Pillow (==9.0.0)
Requires-Dist: pyparsing (==3.0.7)
Requires-Dist: python-dateutil (==2.8.2)
Requires-Dist: six (==1.16.0)
